README.md
setup.cfg
setup.py
heroku_cli_wrapper/__init__.py
heroku_cli_wrapper/helper.py
heroku_cli_wrapper/heroku.py
heroku_cli_wrapper.egg-info/PKG-INFO
heroku_cli_wrapper.egg-info/SOURCES.txt
heroku_cli_wrapper.egg-info/dependency_links.txt
heroku_cli_wrapper.egg-info/top_level.txt