Metadata-Version: 1.0
Name: heroku-cli-wrapper
Version: 0.0.6
Summary: Heroku CLI Wrapper
Home-page: https://github.com/grmmvv/heroku-cli-wrapper
Author: Max Gribennikov
Author-email: grmmvv@gmail.com
License: UNKNOWN
Platform: UNKNOWN
